ipvalidator/__init__.py
ipvalidator/ipvalidator.py
ipvalidator-1.0.0.dist-info/LICENSE
ipvalidator-1.0.0.dist-info/METADATA
ipvalidator-1.0.0.dist-info/WHEEL
ipvalidator-1.0.0.dist-info/top_level.txt
ipvalidator-1.0.0.dist-info/RECORD
